dndice2/__init__.py
dndice2/dice.py
dndice2-0.0.3.dist-info/METADATA
dndice2-0.0.3.dist-info/WHEEL
dndice2-0.0.3.dist-info/licenses/LICENSE.txt
dndice2-0.0.3.dist-info/RECORD
