Metadata-Version: 2.1
Name: dndice2
Version: 0.0.3
Summary: A small dice package for DnD
Author: Steve A
License-File: LICENSE.txt
Classifier: License :: OSI Approved :: MIT License
Classifier: Operating System :: OS Independent
Classifier: Programming Language :: Python :: 3
Requires-Python: >=3.7
